{
  "main": {
    "id": "86a5378843e203b7",
    "type": "split",
    "children": [
      {
        "id": "2f83300cc164b8f4",
        "type": "tabs",
        "children": [
          {
            "id": "5c6ea2d7446abe32",
            "type": "leaf",
            "state": {
              "type": "empty",
              "state": {},
              "icon": "lucide-file",
              "title": "New tab"
            }
          }
        ]
      }
    ],
    "direction": "vertical"
  },
  "left": {
    "id": "e7ffc3bdf7b4d3fb",
    "type": "split",
    "children": [
      {
        "id": "617952aa5b7bf16f",
        "type": "tabs",
        "children": [
          {
            "id": "4bf7197f1e1cd03a",
            "type": "leaf",
            "state": {
              "type": "file-explorer",
              "state": {
                "sortOrder": "alphabetical",
                "autoReveal": false
              },
              "icon": "lucide-folder-closed",
              "title": "Files"
            }
          },
          {
            "id": "cdbb7a6e732a3bbb",
            "type": "leaf",
            "state": {
              "type": "search",
              "state": {
                "query": "",
                "matchingCase": false,
                "explainSearch": false,
                "collapseAll": false,
                "extraContext": false,
                "sortOrder": "alphabetical"
              },
              "icon": "lucide-search",
              "title": "Buscar"
            }
          },
          {
            "id": "941ada81a2d2458c",
            "type": "leaf",
            "state": {
              "type": "bookmarks",
              "state": {},
              "icon": "lucide-bookmark",
              "title": "Marcadores"
            }
          }
        ]
      }
    ],
    "direction": "horizontal",
    "width": 300,
    "collapsed": true
  },
  "right": {
    "id": "c018095f6bb8c856",
    "type": "split",
    "children": [
      {
        "id": "024534cddb85b26b",
        "type": "tabs",
        "children": [
          {
            "id": "28007ec254dc8dd5",
            "type": "leaf",
            "state": {
              "type": "backlink",
              "state": {
                "file": "GhostTrace.md",
                "collapseAll": false,
                "extraContext": false,
                "sortOrder": "alphabetical",
                "showSearch": false,
                "searchQuery": "",
                "backlinkCollapsed": false,
                "unlinkedCollapsed": true
              },
              "icon": "links-coming-in",
              "title": "Enlaces entrantes de GhostTrace"
            }
          },
          {
            "id": "c227293d2711fe13",
            "type": "leaf",
            "state": {
              "type": "outgoing-link",
              "state": {
                "file": "GhostTrace.md",
                "linksCollapsed": false,
                "unlinkedCollapsed": true
              },
              "icon": "links-going-out",
              "title": "Enlaces salientes de GhostTrace"
            }
          },
          {
            "id": "e9875d8924715d90",
            "type": "leaf",
            "state": {
              "type": "tag",
              "state": {
                "sortOrder": "frequency",
                "useHierarchy": true,
                "showSearch": false,
                "searchQuery": ""
              },
              "icon": "lucide-tags",
              "title": "Etiquetas"
            }
          },
          {
            "id": "2ee30ec664e2a6ff",
            "type": "leaf",
            "state": {
              "type": "all-properties",
              "state": {
                "sortOrder": "frequency",
                "showSearch": false,
                "searchQuery": ""
              },
              "icon": "lucide-archive",
              "title": "Todas las propiedades"
            }
          },
          {
            "id": "f564f3d230bffbb8",
            "type": "leaf",
            "state": {
              "type": "outline",
              "state": {
                "file": "GhostTrace.md",
                "followCursor": false,
                "showSearch": false,
                "searchQuery": ""
              },
              "icon": "lucide-list",
              "title": "Esquema de GhostTrace"
            }
          }
        ]
      }
    ],
    "direction": "horizontal",
    "width": 300,
    "collapsed": true
  },
  "left-ribbon": {
    "hiddenItems": {
      "switcher:Open quick switcher": false,
      "graph:Open graph view": false,
      "canvas:Create new canvas": false,
      "daily-notes:Open today's daily note": false,
      "templates:Insert template": false,
      "command-palette:Open command palette": false,
      "bases:Create new base": false
    }
  },
  "active": "5c6ea2d7446abe32",
  "lastOpenFiles": [
    "GhostTrace.md",
    "Pasted image 20260419175241.png"
  ]
}